LICENSE
README.md
setup.py
ldn/__init__.py
ldn/queue.py
ldn/streams.py
ldn/util.py
ldn/wlan.py
ldn.egg-info/PKG-INFO
ldn.egg-info/SOURCES.txt
ldn.egg-info/dependency_links.txt
ldn.egg-info/requires.txt
ldn.egg-info/top_level.txt