Metadata-Version: 2.4
Name: ldn
Version: 0.0.12
Summary: Python package for local wireless communication with a Nintendo Switch.
Home-page: https://github.com/kinnay/LDN
Author: Yannik Marchand
Author-email: ymarchand@me.com
License: GPLv3
Platform: Linux
License-File: LICENSE
Requires-Dist: python-netlink==0.0.10
Requires-Dist: pycryptodome
Dynamic: author
Dynamic: author-email
Dynamic: description
Dynamic: home-page
Dynamic: license
Dynamic: license-file
Dynamic: platform
Dynamic: requires-dist
Dynamic: summary
